nonebot_plugin_mcstatus/__init__.py
nonebot_plugin_mcstatus/data.py
nonebot_plugin_mcstatus/handle.py
nonebot_plugin_mcstatus/parser.py
nonebot_plugin_mcstatus-0.1.8.dist-info/WHEEL
nonebot_plugin_mcstatus-0.1.8.dist-info/METADATA
nonebot_plugin_mcstatus-0.1.8.dist-info/licenses/LICENSE
nonebot_plugin_mcstatus-0.1.8.dist-info/RECORD
