Metadata-Version: 2.1
Name: nonebot-plugin-mcstatus
Version: 0.1.8
Summary: Check Minecraft server status
License: MIT
Author-email: Jigsaw <j1g5aw@foxmail.com>
Requires-Python: >=3.8,<4.0
Requires-Dist: mcstatus<11.0.0,>=10.0.1
Requires-Dist: nonebot-adapter-onebot<3.0.0,>=2.2.2
Requires-Dist: nonebot-plugin-apscheduler<1.0.0,>=0.3.0
Requires-Dist: nonebot2<3.0.0,>=2.0.0
Project-URL: homepage, https://github.com/nonepkg/plugin-mcstatus
Project-URL: repository, https://github.com/nonepkg/plugin-mcstatus
